odoo/addons/mrp_production_category_notes/README.rst
odoo/addons/mrp_production_category_notes/__init__.py
odoo/addons/mrp_production_category_notes/__manifest__.py
odoo/addons/mrp_production_category_notes/i18n/es.po
odoo/addons/mrp_production_category_notes/models/__init__.py
odoo/addons/mrp_production_category_notes/models/mrp_production.py
odoo/addons/mrp_production_category_notes/models/product_category.py
odoo/addons/mrp_production_category_notes/readme/CONTRIBUTORS.rst
odoo/addons/mrp_production_category_notes/readme/DESCRIPTION.rst
odoo/addons/mrp_production_category_notes/readme/INSTALL.rst
odoo/addons/mrp_production_category_notes/readme/USAGE.rst
odoo/addons/mrp_production_category_notes/static/description/icon.png
odoo/addons/mrp_production_category_notes/static/description/index.html
odoo/addons/mrp_production_category_notes/tests/__init__.py
odoo/addons/mrp_production_category_notes/tests/test_mrp_produccion_category_notes.py
odoo/addons/mrp_production_category_notes/views/product_category_views.xml
odoo_addon_mrp_production_category_notes-15.0.1.0.0.1.dist-info/METADATA
odoo_addon_mrp_production_category_notes-15.0.1.0.0.1.dist-info/WHEEL
odoo_addon_mrp_production_category_notes-15.0.1.0.0.1.dist-info/top_level.txt
odoo_addon_mrp_production_category_notes-15.0.1.0.0.1.dist-info/RECORD
