Metadata-Version: 2.1
Name: odoo-addon-mrp_production_category_notes
Version: 15.0.1.0.0.1
Summary: This module adds a new field to product categories that allows adding notes to mrp orders.
Home-page: https://github.com/sygel-technology/sy-manufacture
Author: Sygel, Odoo Community Association (OCA)
Author-email: support@odoo-community.org
License: AGPL-3
Classifier: Programming Language :: Python
Classifier: Framework :: Odoo
Classifier: Framework :: Odoo :: 15.0
Classifier: License :: OSI Approved :: GNU Affero General Public License v3
Requires-Python: >=3.8
Requires-Dist: odoo-addon-mrp-production-note<15.1dev,>=15.0dev
Requires-Dist: odoo<15.1dev,>=15.0a
